Workbook
Name Aporte: Planilha1!$E$24
Name aporte_por_perfil: Planilha1!$E$47
Name dividendo_mensal: Planilha1!$E$27
Name dividendos: Planilha1!$F$19
Name dividendos_FII: Planilha1!$F$19
Name Inflação_media: Planilha1!$F$17
Name patrimonio: Planilha1!$E$26
Name Perfi_investidor: Planilha1!$E$46
Name qnt_anos: Planilha1!$E$25
Name Rendimento_Carteira: Planilha1!#REF!
Name Salario: Planilha1!$E$17
Name Salário: Planilha1!$E$17
Name sugestao_investimento: Planilha1!$E$19
Name taxa_mensal: Planilha1!$E$18
Name valorização_FII: Planilha1!$F$21

Sheet Planilha1
B16: CONFIGURAÇÕES | F16: INFLAÇÃO MÉDIA XXI
B17: Salário | E17: 3000 | F17: =AVERAGE(Planilha2!H9:H34) -> 0.061226923
B18: Retorno Total Mensal | E18: =dividendos -> 0.011 | F18: Dividendos FII
B19: Sugestão De Investimento | E19: =E17*30% -> 900 | F19: =VLOOKUP(E20,Planilha2!B28:C31,2,0) -> 0.011
B20: Cenário | E20: Otimista | F20: Valorização
F21: 0.005
B23: INVESTIMENTO MENSAL
B24: Quanto Investir Por Mês? | E24: =sugestao_investimento -> 900
B25: Por Quantos Anos? | E25: 5
B26: Patrimônio acumulado? | E26: =FV(taxa_mensal,qnt_anos*12,Aporte*-1) -> 75913.582
B27: Dividendo Mensais? | E27: =E26*taxa_mensal -> 835.0494
B29: ANOS DE INVESTIMENTO | C29: PATRIMÔNIO NOMINAL | D29: PATRIMÔNIO REAL | E29: DIVIDENDOS MENSAIS
A30: 2 | B30: Patrimonio em 2 anos | C30: =FV(taxa_mensal+valorização_FII,Planilha2!B35*12,Aporte*-1) -> 26082.541 | D30: =C30/(1+Inflação_media) -> 24577.722 | E30: =(C30*taxa_mensal)/(1+valorização_FII) -> 285.48055
A31: 5 | B31: Patrimonio em 5 anos | C31: =FV(taxa_mensal+valorização_FII,Planilha2!B36*12,Aporte*-1) -> 89545.797 | D31: =C31/(1+Inflação_media) -> 84379.5 | E31: =(C31*taxa_mensal)/(1+valorização_FII) -> 980.10325
A32: 10 | B32: Patrimonio em 10 anos | C32: =FV(taxa_mensal+valorização_FII,Planilha2!B37*12,Aporte*-1) -> 321641.81 | D32: =C32/(1+Inflação_media) -> 303084.86 | E32: =(C32*taxa_mensal)/(1+valorização_FII) -> 3520.4576
A33: 20 | B33: Patrimonio em 20 anos | C33: =FV(taxa_mensal+valorização_FII,Planilha2!B38*12,Aporte*-1) -> 2482456.1 | D33: =C33/(1+Inflação_media) -> 2339232.2 | E33: =(C33*taxa_mensal)/(1+valorização_FII) -> 27171.162
A34: 30 | B34: Patrimonio em 30 anos | C34: =FV(taxa_mensal+valorização_FII,Planilha2!B39*12,Aporte*-1) -> 16998972 | D34: =C34/(1+Inflação_media) -> 16018226 | E34: =(C34*taxa_mensal)/(1+valorização_FII) -> 186058.4
B46: PERFIL DO INVESTIDOR | E46: CONSERVADOR
B47: VALOR DE APORTE | E47: =sugestao_investimento -> 900
B48: TIPO DE FII | C48: PERCENTUAL SUGERIDO | E48: valores
B49: Papel | C49: =VLOOKUP($E$46&"-"&B49,Planilha2!B:F,4,0) -> 0.3 | E49: =$E$47*C49 -> 270
B50: Tijolo | C50: =VLOOKUP($E$46&"-"&B50,Planilha2!B:F,4,0) -> 0.5 | E50: =$E$47*C50 -> 450
B51: Hibridos | C51: =VLOOKUP($E$46&"-"&B51,Planilha2!B:F,4,0) -> 0.1 | E51: =$E$47*C51 -> 90
B52: FOFs | C52: =VLOOKUP($E$46&"-"&B52,Planilha2!B:F,4,0) -> 0.1 | E52: =$E$47*C52 -> 90
B53: Desenvolvimento | C53: =VLOOKUP($E$46&"-"&B53,Planilha2!B:F,4,0) -> 0 | E53: =$E$47*C53 -> 0
B54: Hotelaria | C54: =VLOOKUP($E$46&"-"&B54,Planilha2!B:F,4,0) -> 0 | E54: =$E$47*C54 -> 0
E55: =SUM(E49:E54) -> 900

Sheet Planilha2
B8: chave | C8: PERFIL | D8: TIPO DE FII | E8: PERCENTUAL SUGERIDO | G8: ano | H8: inflação
B9: =C9&"-"&D9 -> conservador-Papel | C9: conservador | D9: Papel | E9: 0.3 | G9: 2000 | H9: 0.0597
B10: =C10&"-"&D10 -> conservador-Tijolo | C10: conservador | D10: Tijolo | E10: 0.5 | G10: 2001 | H10: 0.0767
B11: =C11&"-"&D11 -> conservador-Hibridos | C11: conservador | D11: Hibridos | E11: 0.1 | G11: 2002 | H11: 0.1253
B12: =C12&"-"&D12 -> conservador-FOFs | C12: conservador | D12: FOFs | E12: 0.1 | G12: 2003 | H12: 0.093
B13: =C13&"-"&D13 -> conservador-Desenvolvimento | C13: conservador | D13: Desenvolvimento | E13: 0 | G13: 2004 | H13: 0.076
B14: =C14&"-"&D14 -> conservador-Hotelaria | C14: conservador | D14: Hotelaria | E14: 0 | G14: 2005 | H14: 0.0569
B15: =C15&"-"&D15 -> moderado-Papel | C15: moderado | D15: Papel | E15: 0.27 | G15: 2006 | H15: 0.0314
B16: =C16&"-"&D16 -> moderado-Tijolo | C16: moderado | D16: Tijolo | E16: 0.35 | G16: 2007 | H16: 0.0446
B17: =C17&"-"&D17 -> moderado-Hibridos | C17: moderado | D17: Hibridos | E17: 0.08 | G17: 2008 | H17: 0.059
B18: =C18&"-"&D18 -> moderado-FOFs | C18: moderado | D18: FOFs | E18: 0.1 | G18: 2009 | H18: 0.0431
B19: =C19&"-"&D19 -> moderado-Desenvolvimento | C19: moderado | D19: Desenvolvimento | E19: 0.1 | G19: 2010 | H19: 0.0591
B20: =C20&"-"&D20 -> moderado-Hotelaria | C20: moderado | D20: Hotelaria | E20: 0.1 | G20: 2011 | H20: 0.065
... B26: =C26&"-"&D26 -> agressivo-Hotelaria | C26: agressivo | D26: Hotelaria | E26: 0.1 | G26: 2017 | H26: 0.0295
G27: 2018 | H27: 0.0375
B28: cenário | G28: 2019 | H28: 0.0431
B29: Otimista | C29: 0.011 | G29: 2020 | H29: 0.0452
B30: Moderado | C30: 0.009 | G30: 2021 | H30: 0.1006
B31: Pessimista | C31: 0.007 | G31: 2022 | H31: 0.0579
G32: 2023 | H32: 0.0462
G33: 2024 | H33: 0.0483
B34: anos do cenário | G34: 2025 | H34: 0.0426
B35: 2 | G35: média | H35: =AVERAGE(H9:H34) -> 0.061226923
B36: 5
B37: 10
B38: 20
B39: 30
